pycurd/__init__.py
pycurd/const.py
pycurd/crud/__init__.py
pycurd/crud/_core_crud.py
pycurd/crud/base_crud.py
pycurd/crud/ext/__init__.py
pycurd/crud/ext/peewee_crud.py
pycurd/crud/ext/tortoise_crud.py
pycurd/crud/query_result_row.py
pycurd/crud/sql_crud.py
pycurd/error.py
pycurd/permission.py
pycurd/pydantic_ext/__init__.py
pycurd/pydantic_ext/hex_string.py
pycurd/query.py
pycurd/types.py
pycurd/utils/__init__.py
pycurd/utils/cls_property.py
pycurd/utils/json_ex.py
pycurd/utils/name_helper.py
pycurd/values.py
pycurd-0.2.3.dist-info/LICENSE
pycurd-0.2.3.dist-info/WHEEL
pycurd-0.2.3.dist-info/METADATA
pycurd-0.2.3.dist-info/RECORD
