Metadata-Version: 2.1
Name: pycurd
Version: 0.2.3
Summary: A common crud framework for web.
Home-page: https://github.com/fy0/pycrud
License: MIT
Author: fy
Author-email: fy0748@gmail.com
Requires-Python: >=3.6.9
Classifier: License :: OSI Approved :: MIT License
Classifier: Programming Language :: Python :: 3
Classifier: Programming Language :: Python :: 3.7
Classifier: Programming Language :: Python :: 3.8
Classifier: Programming Language :: Python :: 3.9
Requires-Dist: PyPika (>=0.42.1)
Requires-Dist: multidict (>=4.5,<6.0)
Requires-Dist: pydantic (>=1.6.1)
Requires-Dist: typing_extensions (>=3.6.5)
Project-URL: Repository, https://github.com/fy0/pycrud
